elasticsearch_mcp_server/__init__.py
elasticsearch_mcp_server/__main__.py
elasticsearch_mcp_server/cli.py
elasticsearch_mcp_server/client.py
elasticsearch_mcp_server/config.py
elasticsearch_mcp_server/server.py
elasticsearch_mcp_server/tools.py
sugon_mcp_server_elasticsearch-0.1.0.dist-info/METADATA
sugon_mcp_server_elasticsearch-0.1.0.dist-info/WHEEL
sugon_mcp_server_elasticsearch-0.1.0.dist-info/entry_points.txt
sugon_mcp_server_elasticsearch-0.1.0.dist-info/licenses/LICENSE
sugon_mcp_server_elasticsearch-0.1.0.dist-info/RECORD
