Metadata-Version: 2.4
Name: sugon-mcp-server-elasticsearch
Version: 0.1.0
Summary: MCP server for core Elasticsearch features
Author: sugoncloud
Maintainer: sugoncloud
License-Expression: Apache-2.0
License-File: LICENSE
Keywords: elasticsearch,mcp,model-context-protocol,search,server
Classifier: Development Status :: 3 - Alpha
Classifier: Intended Audience :: Developers
Classifier: License :: OSI Approved :: Apache Software License
Classifier: Operating System :: OS Independent
Classifier: Programming Language :: Python :: 3
Classifier: Programming Language :: Python :: 3.12
Classifier: Programming Language :: Python :: 3.13
Classifier: Topic :: Database :: Database Engines/Servers
Classifier: Topic :: Internet :: WWW/HTTP :: Indexing/Search
Classifier: Topic :: Software Development :: Libraries :: Python Modules
Requires-Python: >=3.12
Requires-Dist: aiohttp>=3.8.0
Requires-Dist: anyio>=4.0.0
Requires-Dist: click>=8.0.0
Requires-Dist: elasticsearch<9.0.0,>=8.0.0
Requires-Dist: mcp>=1.0.0
Requires-Dist: pydantic-settings>=2.0.0
Requires-Dist: pydantic>=2.0.0
Requires-Dist: pyjson5>=1.6.0
Requires-Dist: python-dotenv>=1.0.0
Requires-Dist: starlette>=0.27.0
Requires-Dist: structlog>=23.0.0
Requires-Dist: uvicorn>=0.24.0
Provides-Extra: dev
Requires-Dist: black>=23.0.0; extra == 'dev'
Requires-Dist: flake8>=6.0.0; extra == 'dev'
Requires-Dist: isort>=5.12.0; extra == 'dev'
Requires-Dist: mypy>=1.0.0; extra == 'dev'
Requires-Dist: pre-commit>=3.0.0; extra == 'dev'
Requires-Dist: pytest-asyncio>=0.21.0; extra == 'dev'
Requires-Dist: pytest-cov>=4.0.0; extra == 'dev'
Requires-Dist: pytest>=7.0.0; extra == 'dev'
